discovery/__init__.py
discovery/__main__.py
discovery/_logger.py
discovery/checks.py
discovery/client.py
discovery/exceptions.py
discovery/utils.py
discovery/api/__init__.py
discovery/api/abc.py
discovery/api/acl.py
discovery/api/acl_link.py
discovery/api/agent.py
discovery/api/area.py
discovery/api/auth_method.py
discovery/api/autopilot.py
discovery/api/behavior.py
discovery/api/binding_rule.py
discovery/api/ca.py
discovery/api/catalog.py
discovery/api/check_status.py
discovery/api/checks.py
discovery/api/config.py
discovery/api/connect.py
discovery/api/coordinate.py
discovery/api/events.py
discovery/api/health.py
discovery/api/health_state.py
discovery/api/intention.py
discovery/api/intention_by.py
discovery/api/intention_filter.py
discovery/api/intentions_action.py
discovery/api/keyring.py
discovery/api/kind.py
discovery/api/kv.py
discovery/api/license.py
discovery/api/loglevel.py
discovery/api/namespace.py
discovery/api/operator.py
discovery/api/policy.py
discovery/api/query.py
discovery/api/raft.py
discovery/api/role.py
discovery/api/segment.py
discovery/api/service.py
discovery/api/session.py
discovery/api/snapshot.py
discovery/api/status.py
discovery/api/token.py
discovery/api/token_locality.py
discovery/api/token_type.py
discovery/api/txn.py
discovery/cli/__init__.py
discovery/engine/__init__.py
discovery/engine/abc.py
discovery/engine/base_response.py
discovery/engine/response.py
discovery/engine/aiohttp/__init__.py
discovery/engine/aiohttp/engine.py
discovery/engine/aiohttp/response.py
discovery/engine/httpx/__init__.py
discovery/engine/httpx/engine.py
discovery/engine/httpx/response.py
tests/__init__.py
tests/conftest.py
tests/unit/__init__.py
tests/unit/setup.py
tests/unit/test_client.py
tests/unit/test_service_module.py
tests/unit/test_utils.py
tests/unit/api/__init__.py
tests/unit/api/test_acl.py
tests/unit/api/test_agent.py
tests/unit/api/test_area.py
tests/unit/api/test_auth_method.py
tests/unit/api/test_autopilot.py
discovery_client-1.0.3.dist-info/LICENSE
discovery_client-1.0.3.dist-info/METADATA
discovery_client-1.0.3.dist-info/WHEEL
discovery_client-1.0.3.dist-info/entry_points.txt
discovery_client-1.0.3.dist-info/top_level.txt
discovery_client-1.0.3.dist-info/RECORD
