Metadata-Version: 2.1
Name: discovery-client
Version: 1.0.3
Summary: async consul client
Home-page: https://github.com/amenezes/discovery-client
Author: Alexandre Menezes
Author-email: alexandre.fmenezes@gmail.com
License: Apache-2.0
Project-URL: Documentation, https://discovery-client.amenezes.net
Project-URL: Code, https://github.com/amenezes/discovery-client
Project-URL: Issue tracker, https://github.com/amenezes/discovery-client/issues
Project-URL: Changes, https://github.com/amenezes/discovery-client/releases
Keywords: "asyncio","consul","python-consul","python-consul2"
Classifier: Development Status :: 5 - Production/Stable
Classifier: Framework :: AsyncIO
Classifier: Intended Audience :: Developers
Classifier: License :: OSI Approved :: Apache Software License
Classifier: Operating System :: OS Independent
Classifier: Programming Language :: Python :: 3 :: Only
Classifier: Programming Language :: Python :: 3.8
Classifier: Programming Language :: Python :: 3.9
Classifier: Programming Language :: Python :: 3.10
Classifier: Programming Language :: Python :: 3.11
Classifier: Programming Language :: Python :: 3.12
Classifier: Framework :: AsyncIO
Classifier: Intended Audience :: Developers
Classifier: Topic :: System :: Distributed Computing
Classifier: Programming Language :: Python :: Implementation :: CPython
Classifier: Programming Language :: Python :: Implementation :: PyPy
Classifier: Topic :: Software Development :: Libraries
Requires-Python: >=3.8
License-File: LICENSE
Requires-Dist: aiohttp >=3.6.2
Provides-Extra: all
Requires-Dist: mkdocs-material ; extra == 'all'
Requires-Dist: aiohttp >=3.6.2 ; extra == 'all'
Requires-Dist: httpx >=0.16.1 ; extra == 'all'
Requires-Dist: click >=8.1.3 ; extra == 'all'
Requires-Dist: rich >=12.6.0 ; extra == 'all'
Provides-Extra: cli
Requires-Dist: click >=8.1.3 ; extra == 'cli'
Requires-Dist: rich >=12.6.0 ; extra == 'cli'
Provides-Extra: docs
Requires-Dist: mkdocs-material ; extra == 'docs'
Provides-Extra: httpx
Requires-Dist: httpx >=0.16.1 ; extra == 'httpx'
Provides-Extra: httpxcli
Requires-Dist: httpx >=0.16.1 ; extra == 'httpxcli'
Requires-Dist: click >=8.1.3 ; extra == 'httpxcli'
Requires-Dist: rich >=12.6.0 ; extra == 'httpxcli'
